typergame/__init__.py
typergame/functions.py
typergame/inventory.py
typergame/user.py
typergame-0.3.1.dist-info/METADATA
typergame-0.3.1.dist-info/WHEEL
typergame-0.3.1.dist-info/top_level.txt
typergame-0.3.1.dist-info/RECORD
