Metadata-Version: 2.1
Name: typergame
Version: 0.3.1
Summary: A library to easily set up typergames.
Author: drooler
